odoo/addons/purchase_split_wizard_order_type/README.rst
odoo/addons/purchase_split_wizard_order_type/__init__.py
odoo/addons/purchase_split_wizard_order_type/__manifest__.py
odoo/addons/purchase_split_wizard_order_type/i18n/es.po
odoo/addons/purchase_split_wizard_order_type/readme/CONTRIBUTORS.md
odoo/addons/purchase_split_wizard_order_type/readme/DESCRIPTION.md
odoo/addons/purchase_split_wizard_order_type/readme/USAGE.md
odoo/addons/purchase_split_wizard_order_type/static/description/icon.png
odoo/addons/purchase_split_wizard_order_type/static/description/index.html
odoo/addons/purchase_split_wizard_order_type/wizards/__init__.py
odoo/addons/purchase_split_wizard_order_type/wizards/purchase_split_wizard.py
odoo/addons/purchase_split_wizard_order_type/wizards/purchase_split_wizard_views.xml
odoo_addon_purchase_split_wizard_order_type-16.0.1.0.0.1.dist-info/METADATA
odoo_addon_purchase_split_wizard_order_type-16.0.1.0.0.1.dist-info/WHEEL
odoo_addon_purchase_split_wizard_order_type-16.0.1.0.0.1.dist-info/top_level.txt
odoo_addon_purchase_split_wizard_order_type-16.0.1.0.0.1.dist-info/RECORD
